{"about_coc.md":"8f94405b","about_community-guide.md":"f15e29c4","about_faq.md":"c670ca2f","about_releases.md":"153163d8","about_team.md":"7c580d0d","api_application.md":"76bbf5dc","api_built-in-components.md":"cbca8622","api_built-in-directives.md":"eb3e1646","api_built-in-special-attributes.md":"d675e692","api_built-in-special-elements.md":"c754d9c1","api_component-instance.md":"e04d8979","api_composition-api-dependency-injection.md":"79f533fb","api_composition-api-lifecycle.md":"ae1410b6","api_composition-api-setup.md":"3c5b00ae","api_custom-renderer.md":"03cc5cfa","api_general.md":"2aa9361e","api_index.md":"3ce6c3fc","api_options-composition.md":"13e20907","api_options-lifecycle.md":"d2e0529a","api_options-misc.md":"a3b2b620","api_options-rendering.md":"1f22c6dc","api_options-state.md":"7cc69469","api_reactivity-advanced.md":"e60accd3","api_reactivity-core.md":"4f3c15f9","api_reactivity-utilities.md":"89b543b7","api_render-function.md":"a76b3cc8","api_sfc-css-features.md":"1451b08b","api_sfc-script-setup.md":"cdec3742","api_sfc-spec.md":"8def8ff0","api_ssr.md":"7b755c52","api_utility-types.md":"9250c9b8","ecosystem_themes.md":"e9b9c1b3","examples_index.md":"33c5188f","guide_best-practices_accessibility.md":"fcd257a4","guide_best-practices_performance.md":"440c1683","guide_best-practices_production-deployment.md":"aced2172","guide_best-practices_security.md":"23b002c8","guide_built-ins_keep-alive.md":"bf8adb49","guide_built-ins_suspense.md":"2f78dec3","guide_built-ins_teleport.md":"0c59b5da","guide_built-ins_transition-group.md":"41513fa3","guide_built-ins_transition.md":"4f97bdf7","guide_components_async.md":"d985cfff","guide_components_attrs.md":"445816aa","guide_components_events.md":"71ce602f","guide_components_props.md":"7f727ad5","guide_components_provide-inject.md":"1a9d28b1","guide_components_registration.md":"8f365009","guide_components_slots.md":"2f5f0b64","guide_essentials_application.md":"1f7f63ae","guide_essentials_class-and-style.md":"b48adbfd","guide_essentials_component-basics.md":"01b41ca1","guide_essentials_computed.md":"12406228","guide_essentials_conditional.md":"37df2d10","guide_essentials_event-handling.md":"425dc975","guide_essentials_forms.md":"5a21774e","guide_essentials_lifecycle.md":"a1df5269","guide_essentials_list.md":"7be03b10","guide_essentials_reactivity-fundamentals.md":"65b66cba","guide_essentials_template-refs.md":"afd56978","guide_essentials_template-syntax.md":"9682e731","guide_essentials_watchers.md":"d679ce3c","guide_extras_animation.md":"340f2ae4","guide_extras_composition-api-faq.md":"3d07eece","guide_extras_custom-renderer.md":"7deb53dc","guide_extras_reactivity-in-depth.md":"a5b4a109","guide_extras_reactivity-transform.md":"0a88d1f2","guide_extras_render-function.md":"f0e2812c","guide_extras_rendering-mechanism.md":"d2038d65","guide_extras_ways-of-using-vue.md":"6741f8cb","guide_extras_web-components.md":"81c6ec08","guide_introduction.md":"46afc95d","guide_quick-start.md":"b8f91dc9","guide_reusability_composables.md":"260c8826","guide_reusability_custom-directives.md":"c8d351b0","guide_reusability_plugins.md":"5ac0e07f","guide_scaling-up_routing.md":"50f8dc19","guide_scaling-up_sfc.md":"b83a93de","guide_scaling-up_ssr.md":"daf7be22","guide_scaling-up_state-management.md":"cfcbfefd","guide_scaling-up_testing.md":"6d6373b4","guide_scaling-up_tooling.md":"659412ec","guide_typescript_composition-api.md":"a4b36067","guide_typescript_options-api.md":"dc2116d5","guide_typescript_overview.md":"1fcc9305","index.md":"ed142883","partners_64robots.md":"72418e9b","partners_all.md":"cb383371","partners_curotec.md":"9f4a39ff","partners_devsquad.md":"106f9ab0","partners_index.md":"bb071c18","partners_monterail.md":"28f65e16","partners_passionatepeople.md":"9da9cfaa","partners_redberry.md":"0e80fa0d","partners_tighten.md":"065eaea5","partners_vehikl.md":"bc565436","partners_webreinvent.md":"daa69c33","sponsor_index.md":"f1fcce27","style-guide_index.md":"de3c2623","style-guide_rules-essential.md":"174d2efe","style-guide_rules-recommended.md":"02ab33e3","style-guide_rules-strongly-recommended.md":"12921b50","style-guide_rules-use-with-caution.md":"79786c69","translations_index.md":"292db76e","tutorial_index.md":"f4828393"}
