{"about_coc.md":"9d26c40b","about_community-guide.md":"e2edd00b","about_faq.md":"6ccb0baa","about_releases.md":"87e5263b","about_team.md":"31f367f2","api_application.md":"67c4c948","api_built-in-components.md":"0c962a0d","api_built-in-directives.md":"fffa1689","api_built-in-special-attributes.md":"d5765b18","api_built-in-special-elements.md":"d1d0b7ee","api_component-instance.md":"7628a757","api_composition-api-dependency-injection.md":"29500c9a","api_composition-api-lifecycle.md":"a090f2c5","api_composition-api-setup.md":"ef24fc14","api_custom-renderer.md":"4b064b7b","api_general.md":"1a566e0a","api_index.md":"3ab2a152","api_options-composition.md":"682d412e","api_options-lifecycle.md":"31851d64","api_options-misc.md":"5d5c204f","api_options-rendering.md":"332cc611","api_options-state.md":"41021435","api_reactivity-advanced.md":"98b56121","api_reactivity-core.md":"177fc011","api_reactivity-utilities.md":"2db9f079","api_render-function.md":"b13b612e","api_sfc-css-features.md":"78ef7590","api_sfc-script-setup.md":"03f6426f","api_sfc-spec.md":"e993aecb","api_ssr.md":"be2d9649","api_utility-types.md":"b42fbf69","ecosystem_themes.md":"33942c47","examples_index.md":"811d55c5","guide_best-practices_accessibility.md":"c78ee702","guide_best-practices_performance.md":"982ac7b6","guide_best-practices_production-deployment.md":"31baa406","guide_best-practices_security.md":"801d30cf","guide_built-ins_keep-alive.md":"3ac4bd91","guide_built-ins_suspense.md":"d769db0b","guide_built-ins_teleport.md":"53e1eba1","guide_built-ins_transition-group.md":"c843a6cd","guide_built-ins_transition.md":"2fb8faaf","guide_components_async.md":"ee7af92e","guide_components_attrs.md":"e02c769d","guide_components_events.md":"8384dcf8","guide_components_props.md":"57c237a5","guide_components_provide-inject.md":"3c008741","guide_components_registration.md":"e816d3f9","guide_components_slots.md":"43ffbb71","guide_essentials_application.md":"76597613","guide_essentials_class-and-style.md":"647818cf","guide_essentials_component-basics.md":"80bec142","guide_essentials_computed.md":"5b8c8d30","guide_essentials_conditional.md":"71165270","guide_essentials_event-handling.md":"561e22ed","guide_essentials_forms.md":"7de1ef02","guide_essentials_lifecycle.md":"ef80fb80","guide_essentials_list.md":"987f6aed","guide_essentials_reactivity-fundamentals.md":"919268ec","guide_essentials_template-refs.md":"356180c2","guide_essentials_template-syntax.md":"d4dc821f","guide_essentials_watchers.md":"bf90f724","guide_extras_animation.md":"58bccf30","guide_extras_composition-api-faq.md":"b8be5cb4","guide_extras_custom-renderer.md":"9695a7f4","guide_extras_reactivity-in-depth.md":"ae0f129c","guide_extras_reactivity-transform.md":"d4e741c2","guide_extras_render-function.md":"202c5543","guide_extras_rendering-mechanism.md":"4c8cd0af","guide_extras_ways-of-using-vue.md":"dd2e6caf","guide_extras_web-components.md":"b06f969d","guide_introduction.md":"462b984e","guide_quick-start.md":"e2b54e4b","guide_reusability_composables.md":"8fbae68a","guide_reusability_custom-directives.md":"4abc11b6","guide_reusability_plugins.md":"bc937458","guide_scaling-up_routing.md":"b30e0717","guide_scaling-up_sfc.md":"2b083d8f","guide_scaling-up_ssr.md":"3e3a497b","guide_scaling-up_state-management.md":"9d306fe9","guide_scaling-up_testing.md":"eea288d4","guide_scaling-up_tooling.md":"35bcfb1d","guide_typescript_composition-api.md":"4e5d705b","guide_typescript_options-api.md":"4c1282fe","guide_typescript_overview.md":"47556796","index.md":"f1ed5507","partners_64robots.md":"de96bf65","partners_all.md":"f16078f0","partners_curotec.md":"bb80a454","partners_devsquad.md":"cc672530","partners_index.md":"977753fc","partners_monterail.md":"70d4faa5","partners_passionatepeople.md":"0b947245","partners_redberry.md":"4441ed1c","partners_tighten.md":"713b1483","partners_vehikl.md":"4697fa5a","partners_webreinvent.md":"376620d2","sponsor_index.md":"f332b781","style-guide_index.md":"566b1fdf","style-guide_rules-essential.md":"1ccd496e","style-guide_rules-recommended.md":"82d151e5","style-guide_rules-strongly-recommended.md":"c524489f","style-guide_rules-use-with-caution.md":"4c1f12e9","translations_index.md":"8af868d6","tutorial_index.md":"37a8806c"}
